weathergovapi/__init__.py
weathergovapi/alert.py
weathergovapi/baseobject.py
weathergovapi/forecast.py
weathergovapi/period.py
weathergovapi/point.py
weathergovapi-0.2.dist-info/LICENSE
weathergovapi-0.2.dist-info/METADATA
weathergovapi-0.2.dist-info/WHEEL
weathergovapi-0.2.dist-info/top_level.txt
weathergovapi-0.2.dist-info/RECORD
