Metadata-Version: 2.1
Name: weathergovapi
Version: 0.2
Summary: Simple interface for weather.gov
Home-page: https://gitlab.com/blfordham/weather-api
Author: Bryan Fordham
Author-email: bryan@nativesavannah.com
License: UNKNOWN
Platform: UNKNOWN
Classifier: Programming Language :: Python :: 3
Classifier: License :: OSI Approved :: MIT License
Classifier: Operating System :: OS Independent
